solrad/Site.py
solrad/Sky.py
solrad/__init__.py
solrad/auxiliary_funcs.py
solrad/geotime.py
solrad/atmosphere/__init__.py
solrad/atmosphere/aerosol_asymmetry_factor.py
solrad/atmosphere/angstrom_exponent.py
solrad/atmosphere/aod_550nm.py
solrad/atmosphere/ozone_column.py
solrad/atmosphere/single_scattering_albedo.py
solrad/atmosphere/water_column.py
solrad/climate/__init__.py
solrad/climate/pvgis_tmy.py
solrad/radiation/__init__.py
solrad/radiation/diffuse_radiance_model.py
solrad/radiation/direct_radiance_model.py
solrad/radiation/spectral_radiance_model.py
solrad/radiation/spectrl2.py
solrad/sun/__init__.py
solrad/sun/sun.py
solrad/terrain/__init__.py
solrad/terrain/horizon.py
solrad-0.0.3.dist-info/LICENSE.txt
solrad-0.0.3.dist-info/METADATA
solrad-0.0.3.dist-info/WHEEL
solrad-0.0.3.dist-info/top_level.txt
solrad-0.0.3.dist-info/RECORD
