Metadata-Version: 2.1
Name: solrad
Version: 0.0.3
Summary: Simulation and computation of a site's spectral radiance
Author-email: Andrés Yesid Moreno Villa <aymorenov@eafit.edu.co>
Maintainer-email: Andrés Yesid Moreno Villa <aymorenov@eafit.edu.co>
License: Apache License
Project-URL: Documentation, https://readthedocs.org
Project-URL: Repository, https://github.com/Mastercol01/solrad.git
Keywords: radiance,sky radiance,solar radiance,spectral radiance
Classifier: Development Status :: 3 - Alpha
Classifier: Programming Language :: Python
Classifier: Natural Language :: English
Classifier: Topic :: Scientific/Engineering
Requires-Python: >=3.8
License-File: LICENSE.txt
Requires-Dist: pvlib
Requires-Dist: openpyxl
Requires-Dist: pandas
Requires-Dist: matplotlib
Requires-Dist: netCDF4
Requires-Dist: cdsapi
Requires-Dist: requests
Requires-Dist: scipy
Requires-Dist: suntimes
Requires-Dist: pytest
Provides-Extra: dev
Requires-Dist: build ; extra == 'dev'
Requires-Dist: twine ; extra == 'dev'
Requires-Dist: sphinx ; extra == 'dev'
Requires-Dist: myst-parser ; extra == 'dev'
Requires-Dist: furo ; extra == 'dev'
Requires-Dist: notebook ; extra == 'dev'
Requires-Dist: pandoc ; extra == 'dev'
Requires-Dist: nbsphinx ; extra == 'dev'
Requires-Dist: rst-to-myst ; extra == 'dev'
